leme/__init__.py
leme/cli.py
leme/commands/__init__.py
leme/commands/environment_commands.py
leme/commands/install_commands.py
leme/config/__init__.py
leme/config/constants.py
leme/system/__init__.py
leme/system/docker_installer.py
leme/system/environment_manager.py
leme/system/system_detector.py
leme/system/installers/__init__.py
leme/system/installers/aws_cli_installer.py
leme/system/installers/azure_cli_installer.py
leme/system/installers/base_installer.py
leme/system/installers/git_installer.py
leme/system/installers/macos_installer.py
leme/system/installers/redhat_installer.py
leme/system/installers/terraform_installer.py
leme/system/installers/ubuntu_installer.py
leme-1.0.4.dist-info/licenses/LICENSE
leme-1.0.4.dist-info/METADATA
leme-1.0.4.dist-info/WHEEL
leme-1.0.4.dist-info/entry_points.txt
leme-1.0.4.dist-info/top_level.txt
leme-1.0.4.dist-info/RECORD
