Metadata-Version: 2.4
Name: leme
Version: 1.0.4
Summary: CLI for automatic DevOps environment configuration
Author-email: CLI Leme DevOps <dev@example.com>
License: MIT
Project-URL: Homepage, https://github.com/iesodias/projeto_cli
Project-URL: Bug Reports, https://github.com/iesodias/projeto_cli/issues
Project-URL: Source, https://github.com/iesodias/projeto_cli
Project-URL: Documentation, https://github.com/iesodias/projeto_cli#readme
Keywords: devops,cli,docker,terraform,azure,aws,kubernetes,automation
Classifier: Development Status :: 5 - Production/Stable
Classifier: Intended Audience :: Developers
Classifier: Intended Audience :: System Administrators
Classifier: License :: OSI Approved :: MIT License
Classifier: Operating System :: OS Independent
Classifier: Programming Language :: Python :: 3
Classifier: Programming Language :: Python :: 3.8
Classifier: Programming Language :: Python :: 3.9
Classifier: Programming Language :: Python :: 3.10
Classifier: Programming Language :: Python :: 3.11
Classifier: Programming Language :: Python :: 3.12
Classifier: Topic :: Software Development :: Libraries :: Python Modules
Classifier: Topic :: System :: Installation/Setup
Classifier: Topic :: System :: Systems Administration
Requires-Python: >=3.8
License-File: LICENSE
Requires-Dist: typer>=0.16.0
Requires-Dist: rich>=14.0.0
Requires-Dist: jinja2>=3.1.0
Provides-Extra: dev
Requires-Dist: pytest>=7.0.0; extra == "dev"
Requires-Dist: black>=23.0.0; extra == "dev"
Requires-Dist: flake8>=6.0.0; extra == "dev"
Requires-Dist: build>=0.10.0; extra == "dev"
Requires-Dist: twine>=4.0.0; extra == "dev"
Dynamic: license-file
